superposition_sdk/__init__.py
superposition_sdk/auth.py
superposition_sdk/auth_helpers.py
superposition_sdk/client.py
superposition_sdk/config.py
superposition_sdk/deserialize.py
superposition_sdk/models.py
superposition_sdk/serialize.py
superposition_sdk/_private/__init__.py
superposition_sdk/_private/schemas.py
superposition_sdk-0.97.4.dist-info/METADATA
superposition_sdk-0.97.4.dist-info/WHEEL
superposition_sdk-0.97.4.dist-info/RECORD
